[
  {
    "Name": "ACS_St_SchrgTyp_1",
    "Id": "ACS_St_SchrgTyp_1",
    "Description": "ACS_St_SchrgTyp_1",
    "CatAuto_DateTime_CstField_c": "2022-03-01T00:00:00Z",
    "IsActive": true,
    "HasDefaults": false,
    "HasAttributes": false,
    "Version": 1.0,
    "CatAuto_CustomFieldPickList_c": "USD",
    "ConfigurationType": "Standalone",
    "CatAuto_Int_CstField_c": 201,
    "HasSearchAttributes": false,
    "ProductCode": "ACS_St_SchrgTyp_1",
    "CatAuto_String_CstField_c": "AutoString_01",
    "ProductType": null,
    "ImageURL": "https://i1.wp.com/techforceservices.com.au/wp-content/uploads/2019/04/Conga.png?fit=584%2C190&ssl=1",
    "CatAuto_Multipicklist_CstField_c": [
      "Red",
      "Blue"
    ],
    "Uom": "Each",
    "CatAuto_Currency_CstField_c": "USD",
    "ExpirationDate": "2100-12-31T00:00:00Z",
    "CatAuto_Boolean_CstField_c": true,
    "QuantityUnitOfMeasure": null,
    "HasOptions": false,
    "Family": null,
    "CatAuto_Double_CstField_c": 1.0,
    "EffectiveDate": "1900-01-01T00:00:00Z",
    "Prices": [
      {
        "Name": "PI-ACS_PL_PLI_1",
        "Currency": "USD",
        "Id": "ACS_PL_PLI_1",
        "ContractNumber": null,
        "DisableSyncWithOpportunity": false,
        "DefaultQuantityDatasource": null,
        "ProductId": "ACS_St_SchrgTyp_1",
        "DefaultPriceFrom": null,
        "ListPrice": 10.0,
        "DefaultPriceDatasource": null,
        "PriceIncludedInBundle": false,
        "AllocateGroupAdjustment": true,
        "AutoRenewalType": null,
        "PriceUom": "Each",
        "EnableCommitment": false,
        "BillingRule": null,
        "AutoRenewalTerm": null,
        "DisableCostModel": false,
        "SubType": null,
        "BillingFrequency": null,
        "Sequence": null,
        "DefaultQuantityFrom": null,
        "ContractItemNumber": null,
        "DisableAssetIntegration": false,
        "AllowPriceRampOverlap": false,
        "PriceListId": "ACS_PL",
        "PriceMethod": "Per Unit",
        "EffectiveOn": null,
        "MaxPrice": null,
        "PriceType": "One Time",
        "Description": null,
        "IsActive": true,
        "AllowManualAdjustment": true,
        "AutoRenew": false,
        "MinUsageQuantity": null,
        "IsQuantityReadOnly": false,
        "Cost": null,
        "MinPrice": null,
        "AutoCascadeQuantity": false,
        "DefaultQuantity": null,
        "AllowProration": false,
        "HasCriteria": false,
        "DefaultSellingTerm": null,
        "IsSellingTermReadOnly": false,
        "Type": null,
        "ExpirationDate": "2100-12-31T00:00:00Z",
        "ChargeType": "Standard Price",
        "AutoCascadeSellingTerm": false,
        "ContractPrice": null,
        "Frequency": null,
        "IsUsageTierModifiable": false,
        "EffectiveDate": "1900-01-01T00:00:00Z",
        "PriceList": {
          "Currency": "USD",
          "Id": "ACS_PL",
          "Name": "ACS_PL",
          "Account": null,
          "BasedOnAdjustmentAmount": null,
          "BasedOnAdjustmentType": null,
          "ContractNumber": null,
          "Description": "ACS_PL",
          "EffectiveDate": "1900-01-01T00:00:00Z",
          "ExpirationDate": "2100-12-31T00:00:00Z",
          "IsActive": true,
          "Type": "Standard"
        }
      }
    ]
  },
  {
    "Name": "ACS_St_MchrgTyp_1",
    "Id": "ACS_St_MchrgTyp_1",
    "Description": "ACS_St_MchrgTyp_1",
    "CatAuto_DateTime_CstField_c": "2022-03-01T00:00:00Z",
    "IsActive": true,
    "HasDefaults": false,
    "HasAttributes": false,
    "Version": 1.0,
    "CatAuto_CustomFieldPickList_c": "INR",
    "ConfigurationType": "Standalone",
    "CatAuto_Int_CstField_c": 202,
    "HasSearchAttributes": false,
    "ProductCode": "ACS_St_MchrgTyp_1",
    "CatAuto_String_CstField_c": "AutoString_02",
    "ProductType": null,
    "ImageURL": "https://i1.wp.com/techforceservices.com.au/wp-content/uploads/2019/04/Conga.png?fit=584%2C190&ssl=1",
    "CatAuto_Multipicklist_CstField_c": [
      "Yellow",
      "Green"
    ],
    "Uom": "Each",
    "CatAuto_Currency_CstField_c": "INR",
    "ExpirationDate": "2100-12-31T00:00:00Z",
    "CatAuto_Boolean_CstField_c": false,
    "QuantityUnitOfMeasure": null,
    "HasOptions": false,
    "Family": null,
    "CatAuto_Double_CstField_c": 2.0,
    "EffectiveDate": "1900-01-01T00:00:00Z",
    "Prices": [
      {
        "Name": "PI-ACS_PL_PLI_2",
        "Currency": "USD",
        "Id": "ACS_PL_PLI_2",
        "ContractNumber": null,
        "DisableSyncWithOpportunity": false,
        "DefaultQuantityDatasource": null,
        "ProductId": "ACS_St_MchrgTyp_1",
        "DefaultPriceFrom": null,
        "ListPrice": 10.0,
        "DefaultPriceDatasource": null,
        "PriceIncludedInBundle": false,
        "AllocateGroupAdjustment": true,
        "AutoRenewalType": null,
        "PriceUom": "Each",
        "EnableCommitment": false,
        "BillingRule": null,
        "AutoRenewalTerm": null,
        "DisableCostModel": false,
        "SubType": null,
        "BillingFrequency": null,
        "Sequence": null,
        "DefaultQuantityFrom": null,
        "ContractItemNumber": null,
        "DisableAssetIntegration": false,
        "AllowPriceRampOverlap": false,
        "PriceListId": "ACS_PL",
        "PriceMethod": "Per Unit",
        "EffectiveOn": null,
        "MaxPrice": null,
        "PriceType": "One Time",
        "Description": null,
        "IsActive": true,
        "AllowManualAdjustment": true,
        "AutoRenew": false,
        "MinUsageQuantity": null,
        "IsQuantityReadOnly": false,
        "Cost": null,
        "MinPrice": null,
        "AutoCascadeQuantity": false,
        "DefaultQuantity": null,
        "AllowProration": false,
        "HasCriteria": false,
        "DefaultSellingTerm": null,
        "IsSellingTermReadOnly": false,
        "Type": null,
        "ExpirationDate": "2100-12-31T00:00:00Z",
        "ChargeType": "Standard Price",
        "AutoCascadeSellingTerm": false,
        "ContractPrice": null,
        "Frequency": null,
        "IsUsageTierModifiable": false,
        "EffectiveDate": "1900-01-01T00:00:00Z",
        "PriceList": {
          "Currency": "USD",
          "Id": "ACS_PL",
          "Name": "ACS_PL",
          "Account": null,
          "BasedOnAdjustmentAmount": null,
          "BasedOnAdjustmentType": null,
          "ContractNumber": null,
          "Description": "ACS_PL",
          "EffectiveDate": "1900-01-01T00:00:00Z",
          "ExpirationDate": "2100-12-31T00:00:00Z",
          "IsActive": true,
          "Type": "Standard"
        }
      }
    ]
  },
  {
    "Name": "ACS_St_NtAsC_1",
    "Id": "ACS_St_NtAsC_1",
    "Description": "ACS_St_NtAsC_1",
    "CatAuto_DateTime_CstField_c": "2022-03-01T00:00:00Z",
    "IsActive": true,
    "HasDefaults": false,
    "HasAttributes": false,
    "Version": 1.0,
    "CatAuto_CustomFieldPickList_c": "GBP",
    "ConfigurationType": "Standalone",
    "CatAuto_Int_CstField_c": 203,
    "HasSearchAttributes": false,
    "ProductCode": "ACS_St_NtAsC_1",
    "CatAuto_String_CstField_c": "AutoString_03",
    "ProductType": null,
    "ImageURL": "https://i1.wp.com/techforceservices.com.au/wp-content/uploads/2019/04/Conga.png?fit=584%2C190&ssl=1",
    "CatAuto_Multipicklist_CstField_c": [
      "Pink",
      "White"
    ],
    "Uom": "Each",
    "CatAuto_Currency_CstField_c": "GBP",
    "ExpirationDate": "2100-12-31T00:00:00Z",
    "CatAuto_Boolean_CstField_c": true,
    "QuantityUnitOfMeasure": null,
    "HasOptions": false,
    "Family": null,
    "CatAuto_Double_CstField_c": 3.0,
    "EffectiveDate": "1900-01-01T00:00:00Z",
    "Prices": [
      {
        "Name": "PI-ACS_PL_PLI_4",
        "Currency": "USD",
        "Id": "ACS_PL_PLI_4",
        "ContractNumber": null,
        "DisableSyncWithOpportunity": false,
        "DefaultQuantityDatasource": null,
        "ProductId": "ACS_St_NtAsC_1",
        "DefaultPriceFrom": null,
        "ListPrice": 10.0,
        "DefaultPriceDatasource": null,
        "PriceIncludedInBundle": false,
        "AllocateGroupAdjustment": true,
        "AutoRenewalType": null,
        "PriceUom": "Each",
        "EnableCommitment": false,
        "BillingRule": null,
        "AutoRenewalTerm": null,
        "DisableCostModel": false,
        "SubType": null,
        "BillingFrequency": null,
        "Sequence": null,
        "DefaultQuantityFrom": null,
        "ContractItemNumber": null,
        "DisableAssetIntegration": false,
        "AllowPriceRampOverlap": false,
        "PriceListId": "ACS_PL",
        "PriceMethod": "Per Unit",
        "EffectiveOn": null,
        "MaxPrice": null,
        "PriceType": "One Time",
        "Description": null,
        "IsActive": true,
        "AllowManualAdjustment": true,
        "AutoRenew": false,
        "MinUsageQuantity": null,
        "IsQuantityReadOnly": false,
        "Cost": null,
        "MinPrice": null,
        "AutoCascadeQuantity": false,
        "DefaultQuantity": null,
        "AllowProration": false,
        "HasCriteria": false,
        "DefaultSellingTerm": null,
        "IsSellingTermReadOnly": false,
        "Type": null,
        "ExpirationDate": "2100-12-31T00:00:00Z",
        "ChargeType": "Standard Price",
        "AutoCascadeSellingTerm": false,
        "ContractPrice": null,
        "Frequency": null,
        "IsUsageTierModifiable": false,
        "EffectiveDate": "1900-01-01T00:00:00Z",
        "PriceList": {
          "Currency": "USD",
          "Id": "ACS_PL",
          "Name": "ACS_PL",
          "Account": null,
          "BasedOnAdjustmentAmount": null,
          "BasedOnAdjustmentType": null,
          "ContractNumber": null,
          "Description": "ACS_PL",
          "EffectiveDate": "1900-01-01T00:00:00Z",
          "ExpirationDate": "2100-12-31T00:00:00Z",
          "IsActive": true,
          "Type": "Standard"
        }
      }
    ]
  },
  {
    "Name": "ACS_St_NtAsC_2",
    "Id": "ACS_St_NtAsC_2",
    "Description": "ACS_St_NtAsC_2",
    "CatAuto_DateTime_CstField_c": "2018-03-01T00:00:00Z",
    "IsActive": true,
    "HasDefaults": false,
    "HasAttributes": false,
    "Version": 1.0,
    "CatAuto_CustomFieldPickList_c": "EUR",
    "ConfigurationType": "Standalone",
    "CatAuto_Int_CstField_c": 204,
    "HasSearchAttributes": false,
    "ProductCode": "ACS_St_NtAsC_2",
    "CatAuto_String_CstField_c": "AutoString_04",
    "ProductType": null,
    "ImageURL": "https://i1.wp.com/techforceservices.com.au/wp-content/uploads/2019/04/Conga.png?fit=584%2C190&ssl=1",
    "CatAuto_Multipicklist_CstField_c": [
      "Purple",
      "Black"
    ],
    "Uom": "Each",
    "CatAuto_Currency_CstField_c": "USD",
    "ExpirationDate": "2100-12-31T00:00:00Z",
    "CatAuto_Boolean_CstField_c": false,
    "QuantityUnitOfMeasure": null,
    "HasOptions": false,
    "Family": null,
    "CatAuto_Double_CstField_c": 4.0,
    "EffectiveDate": "1900-01-01T00:00:00Z",
    "Prices": [
      {
        "Name": "PI-ACS_PL_PLI_5",
        "Currency": "USD",
        "Id": "ACS_PL_PLI_5",
        "ContractNumber": null,
        "DisableSyncWithOpportunity": false,
        "DefaultQuantityDatasource": null,
        "ProductId": "ACS_St_NtAsC_2",
        "DefaultPriceFrom": null,
        "ListPrice": 10.0,
        "DefaultPriceDatasource": null,
        "PriceIncludedInBundle": false,
        "AllocateGroupAdjustment": true,
        "AutoRenewalType": null,
        "PriceUom": "Each",
        "EnableCommitment": false,
        "BillingRule": null,
        "AutoRenewalTerm": null,
        "DisableCostModel": false,
        "SubType": null,
        "BillingFrequency": null,
        "Sequence": null,
        "DefaultQuantityFrom": null,
        "ContractItemNumber": null,
        "DisableAssetIntegration": false,
        "AllowPriceRampOverlap": false,
        "PriceListId": "ACS_PL",
        "PriceMethod": "Per Unit",
        "EffectiveOn": null,
        "MaxPrice": null,
        "PriceType": "One Time",
        "Description": null,
        "IsActive": true,
        "AllowManualAdjustment": true,
        "AutoRenew": false,
        "MinUsageQuantity": null,
        "IsQuantityReadOnly": false,
        "Cost": null,
        "MinPrice": null,
        "AutoCascadeQuantity": false,
        "DefaultQuantity": null,
        "AllowProration": false,
        "HasCriteria": false,
        "DefaultSellingTerm": null,
        "IsSellingTermReadOnly": false,
        "Type": null,
        "ExpirationDate": "2100-12-31T00:00:00Z",
        "ChargeType": "Standard Price",
        "AutoCascadeSellingTerm": false,
        "ContractPrice": null,
        "Frequency": null,
        "IsUsageTierModifiable": false,
        "EffectiveDate": "1900-01-01T00:00:00Z",
        "PriceList": {
          "Currency": "USD",
          "Id": "ACS_PL",
          "Name": "ACS_PL",
          "Account": null,
          "BasedOnAdjustmentAmount": null,
          "BasedOnAdjustmentType": null,
          "ContractNumber": null,
          "Description": "ACS_PL",
          "EffectiveDate": "1900-01-01T00:00:00Z",
          "ExpirationDate": "2100-12-31T00:00:00Z",
          "IsActive": true,
          "Type": "Standard"
        }
      }
    ]
  },
  {
    "Name": "ACS_St_MchrgTyp_2",
    "Id": "ACS_St_MchrgTyp_2",
    "Description": "ACS_St_MchrgTyp_2",
    "CatAuto_DateTime_CstField_c": "2022-03-01T00:00:00Z",
    "IsActive": true,
    "HasDefaults": false,
    "HasAttributes": false,
    "Version": 1.0,
    "CatAuto_CustomFieldPickList_c": "GBP",
    "ConfigurationType": "Standalone",
    "CatAuto_Int_CstField_c": 211,
    "HasSearchAttributes": false,
    "ProductCode": "ACS_St_MchrgTyp_2",
    "CatAuto_String_CstField_c": "AutoString_11",
    "ProductType": null,
    "ImageURL": "https://i1.wp.com/techforceservices.com.au/wp-content/uploads/2019/04/Conga.png?fit=584%2C190&ssl=1",
    "CatAuto_Multipicklist_CstField_c": [
      "Pink",
      "White"
    ],
    "Uom": "Each",
    "CatAuto_Currency_CstField_c": "INR",
    "ExpirationDate": "2100-12-31T00:00:00Z",
    "CatAuto_Boolean_CstField_c": true,
    "QuantityUnitOfMeasure": null,
    "HasOptions": false,
    "Family": null,
    "CatAuto_Double_CstField_c": 11.0,
    "EffectiveDate": "1900-01-01T00:00:00Z",
    "Prices": [
      {
        "Name": "PI-ACS_PL_PLI_11",
        "Currency": "USD",
        "Id": "ACS_PL_PLI_11",
        "ContractNumber": null,
        "DisableSyncWithOpportunity": false,
        "DefaultQuantityDatasource": null,
        "ProductId": "ACS_St_MchrgTyp_2",
        "DefaultPriceFrom": null,
        "ListPrice": 10.0,
        "DefaultPriceDatasource": null,
        "PriceIncludedInBundle": false,
        "AllocateGroupAdjustment": true,
        "AutoRenewalType": null,
        "PriceUom": "Each",
        "EnableCommitment": false,
        "BillingRule": null,
        "AutoRenewalTerm": null,
        "DisableCostModel": false,
        "SubType": null,
        "BillingFrequency": null,
        "Sequence": null,
        "DefaultQuantityFrom": null,
        "ContractItemNumber": null,
        "DisableAssetIntegration": false,
        "AllowPriceRampOverlap": false,
        "PriceListId": "ACS_PL",
        "PriceMethod": "Per Unit",
        "EffectiveOn": null,
        "MaxPrice": null,
        "PriceType": "One Time",
        "Description": null,
        "IsActive": true,
        "AllowManualAdjustment": true,
        "AutoRenew": false,
        "MinUsageQuantity": null,
        "IsQuantityReadOnly": false,
        "Cost": null,
        "MinPrice": null,
        "AutoCascadeQuantity": false,
        "DefaultQuantity": null,
        "AllowProration": false,
        "HasCriteria": false,
        "DefaultSellingTerm": null,
        "IsSellingTermReadOnly": false,
        "Type": null,
        "ExpirationDate": "2100-12-31T00:00:00Z",
        "ChargeType": "Standard Price",
        "AutoCascadeSellingTerm": false,
        "ContractPrice": null,
        "Frequency": null,
        "IsUsageTierModifiable": false,
        "EffectiveDate": "1900-01-01T00:00:00Z",
        "PriceList": {
          "Currency": "USD",
          "Id": "ACS_PL",
          "Name": "ACS_PL",
          "Account": null,
          "BasedOnAdjustmentAmount": null,
          "BasedOnAdjustmentType": null,
          "ContractNumber": null,
          "Description": "ACS_PL",
          "EffectiveDate": "1900-01-01T00:00:00Z",
          "ExpirationDate": "2100-12-31T00:00:00Z",
          "IsActive": true,
          "Type": "Standard"
        }
      }
    ]
  },
  {
    "Name": "ACS_St_MchrgTyp_3",
    "Id": "ACS_St_MchrgTyp_3",
    "Description": "ACS_St_MchrgTyp_3",
    "CatAuto_DateTime_CstField_c": "2000-03-01T00:00:00Z",
    "IsActive": true,
    "HasDefaults": false,
    "HasAttributes": false,
    "Version": 1.0,
    "CatAuto_CustomFieldPickList_c": "EUR",
    "ConfigurationType": "Standalone",
    "CatAuto_Int_CstField_c": 1324,
    "HasSearchAttributes": false,
    "ProductCode": "ACS_St_MchrgTyp_3",
    "CatAuto_String_CstField_c": "AutoString_1124",
    "ProductType": null,
    "ImageURL": "https://i1.wp.com/techforceservices.com.au/wp-content/uploads/2019/04/Conga.png?fit=584%2C190&ssl=1",
    "CatAuto_Multipicklist_CstField_c": [
      "Purple",
      "Black"
    ],
    "Uom": "Each",
    "CatAuto_Currency_CstField_c": "INR",
    "ExpirationDate": "2100-12-31T00:00:00Z",
    "CatAuto_Boolean_CstField_c": false,
    "QuantityUnitOfMeasure": null,
    "HasOptions": false,
    "Family": null,
    "CatAuto_Double_CstField_c": 1124.0,
    "EffectiveDate": "1900-01-01T00:00:00Z",
    "Prices": [
      {
        "Name": "PI-ACS_PL_PLI_26",
        "Currency": "USD",
        "Id": "ACS_PL_PLI_26",
        "ContractNumber": null,
        "DisableSyncWithOpportunity": false,
        "DefaultQuantityDatasource": null,
        "ProductId": "ACS_St_MchrgTyp_3",
        "DefaultPriceFrom": null,
        "ListPrice": 10.0,
        "DefaultPriceDatasource": null,
        "PriceIncludedInBundle": false,
        "AllocateGroupAdjustment": true,
        "AutoRenewalType": null,
        "PriceUom": "Each",
        "EnableCommitment": false,
        "BillingRule": null,
        "AutoRenewalTerm": null,
        "DisableCostModel": false,
        "SubType": null,
        "BillingFrequency": null,
        "Sequence": null,
        "DefaultQuantityFrom": null,
        "ContractItemNumber": null,
        "DisableAssetIntegration": false,
        "AllowPriceRampOverlap": false,
        "PriceListId": "ACS_PL",
        "PriceMethod": "Per Unit",
        "EffectiveOn": null,
        "MaxPrice": null,
        "PriceType": "One Time",
        "Description": null,
        "IsActive": true,
        "AllowManualAdjustment": true,
        "AutoRenew": false,
        "MinUsageQuantity": null,
        "IsQuantityReadOnly": false,
        "Cost": null,
        "MinPrice": null,
        "AutoCascadeQuantity": false,
        "DefaultQuantity": null,
        "AllowProration": false,
        "HasCriteria": false,
        "DefaultSellingTerm": null,
        "IsSellingTermReadOnly": false,
        "Type": null,
        "ExpirationDate": "2100-12-31T00:00:00Z",
        "ChargeType": "Standard Price",
        "AutoCascadeSellingTerm": false,
        "ContractPrice": null,
        "Frequency": null,
        "IsUsageTierModifiable": false,
        "EffectiveDate": "1900-01-01T00:00:00Z",
        "PriceList": {
          "Currency": "USD",
          "Id": "ACS_PL",
          "Name": "ACS_PL",
          "Account": null,
          "BasedOnAdjustmentAmount": null,
          "BasedOnAdjustmentType": null,
          "ContractNumber": null,
          "Description": "ACS_PL",
          "EffectiveDate": "1900-01-01T00:00:00Z",
          "ExpirationDate": "2100-12-31T00:00:00Z",
          "IsActive": true,
          "Type": "Standard"
        }
      }
    ]
  },
  {
    "Name": "ACS_St_MchrgTyp_4",
    "Id": "ACS_St_MchrgTyp_4",
    "Description": "ACS_St_MchrgTyp_4",
    "CatAuto_DateTime_CstField_c": "2022-03-01T00:00:00Z",
    "IsActive": true,
    "HasDefaults": false,
    "HasAttributes": false,
    "Version": 1.0,
    "CatAuto_CustomFieldPickList_c": "USD",
    "ConfigurationType": "Standalone",
    "CatAuto_Int_CstField_c": 1325,
    "HasSearchAttributes": false,
    "ProductCode": "ACS_St_MchrgTyp_4",
    "CatAuto_String_CstField_c": "AutoString_1125",
    "ProductType": null,
    "ImageURL": "https://i1.wp.com/techforceservices.com.au/wp-content/uploads/2019/04/Conga.png?fit=584%2C190&ssl=1",
    "CatAuto_Multipicklist_CstField_c": [
      "Red",
      "Blue"
    ],
    "Uom": "Each",
    "CatAuto_Currency_CstField_c": "GBP",
    "ExpirationDate": "2100-12-31T00:00:00Z",
    "CatAuto_Boolean_CstField_c": true,
    "QuantityUnitOfMeasure": null,
    "HasOptions": false,
    "Family": null,
    "CatAuto_Double_CstField_c": 1125.0,
    "EffectiveDate": "1900-01-01T00:00:00Z",
    "Prices": [
      {
        "Name": "PI-ACS_PL_PLI_30",
        "Currency": "USD",
        "Id": "ACS_PL_PLI_30",
        "ContractNumber": null,
        "DisableSyncWithOpportunity": false,
        "DefaultQuantityDatasource": null,
        "ProductId": "ACS_St_MchrgTyp_4",
        "DefaultPriceFrom": null,
        "ListPrice": 10.0,
        "DefaultPriceDatasource": null,
        "PriceIncludedInBundle": false,
        "AllocateGroupAdjustment": true,
        "AutoRenewalType": null,
        "PriceUom": "Each",
        "EnableCommitment": false,
        "BillingRule": null,
        "AutoRenewalTerm": null,
        "DisableCostModel": false,
        "SubType": null,
        "BillingFrequency": null,
        "Sequence": null,
        "DefaultQuantityFrom": null,
        "ContractItemNumber": null,
        "DisableAssetIntegration": false,
        "AllowPriceRampOverlap": false,
        "PriceListId": "ACS_PL",
        "PriceMethod": "Per Unit",
        "EffectiveOn": null,
        "MaxPrice": null,
        "PriceType": "One Time",
        "Description": null,
        "IsActive": true,
        "AllowManualAdjustment": true,
        "AutoRenew": false,
        "MinUsageQuantity": null,
        "IsQuantityReadOnly": false,
        "Cost": null,
        "MinPrice": null,
        "AutoCascadeQuantity": false,
        "DefaultQuantity": null,
        "AllowProration": false,
        "HasCriteria": false,
        "DefaultSellingTerm": null,
        "IsSellingTermReadOnly": false,
        "Type": null,
        "ExpirationDate": "2100-12-31T00:00:00Z",
        "ChargeType": "License Fee",
        "AutoCascadeSellingTerm": false,
        "ContractPrice": null,
        "Frequency": null,
        "IsUsageTierModifiable": false,
        "EffectiveDate": "1900-01-01T00:00:00Z",
        "PriceList": {
          "Currency": "USD",
          "Id": "ACS_PL",
          "Name": "ACS_PL",
          "Account": null,
          "BasedOnAdjustmentAmount": null,
          "BasedOnAdjustmentType": null,
          "ContractNumber": null,
          "Description": "ACS_PL",
          "EffectiveDate": "1900-01-01T00:00:00Z",
          "ExpirationDate": "2100-12-31T00:00:00Z",
          "IsActive": true,
          "Type": "Standard"
        }
      }
    ]
  },
  {
    "Name": "ACS_St_SchrgTyp_MPL_1",
    "Id": "ACS_St_SchrgTyp_MPL_1",
    "Description": "ACS_St_SchrgTyp_MPL_1",
    "CatAuto_DateTime_CstField_c": "2022-03-01T00:00:00Z",
    "IsActive": true,
    "HasDefaults": false,
    "HasAttributes": false,
    "Version": 1.0,
    "CatAuto_CustomFieldPickList_c": "INR",
    "ConfigurationType": "Standalone",
    "CatAuto_Int_CstField_c": 1326,
    "HasSearchAttributes": false,
    "ProductCode": "ACS_St_SchrgTyp_MPL_1",
    "CatAuto_String_CstField_c": "AutoString_1126",
    "ProductType": null,
    "ImageURL": "https://i1.wp.com/techforceservices.com.au/wp-content/uploads/2019/04/Conga.png?fit=584%2C190&ssl=1",
    "CatAuto_Multipicklist_CstField_c": [
      "Yellow",
      "Green"
    ],
    "Uom": "Each",
    "CatAuto_Currency_CstField_c": "USD",
    "ExpirationDate": "2100-12-31T00:00:00Z",
    "CatAuto_Boolean_CstField_c": false,
    "QuantityUnitOfMeasure": null,
    "HasOptions": false,
    "Family": null,
    "CatAuto_Double_CstField_c": 1126.0,
    "EffectiveDate": "1900-01-01T00:00:00Z",
    "Prices": [
      {
        "Name": "PI-ACS_PL_PLI_33",
        "Currency": "USD",
        "Id": "ACS_PL_PLI_33",
        "ContractNumber": null,
        "DisableSyncWithOpportunity": false,
        "DefaultQuantityDatasource": null,
        "ProductId": "ACS_St_SchrgTyp_MPL_1",
        "DefaultPriceFrom": null,
        "ListPrice": 10.0,
        "DefaultPriceDatasource": null,
        "PriceIncludedInBundle": false,
        "AllocateGroupAdjustment": true,
        "AutoRenewalType": null,
        "PriceUom": "Each",
        "EnableCommitment": false,
        "BillingRule": null,
        "AutoRenewalTerm": null,
        "DisableCostModel": false,
        "SubType": null,
        "BillingFrequency": null,
        "Sequence": null,
        "DefaultQuantityFrom": null,
        "ContractItemNumber": null,
        "DisableAssetIntegration": false,
        "AllowPriceRampOverlap": false,
        "PriceListId": "ACS_PL",
        "PriceMethod": "Per Unit",
        "EffectiveOn": null,
        "MaxPrice": null,
        "PriceType": "One Time",
        "Description": null,
        "IsActive": true,
        "AllowManualAdjustment": true,
        "AutoRenew": false,
        "MinUsageQuantity": null,
        "IsQuantityReadOnly": false,
        "Cost": null,
        "MinPrice": null,
        "AutoCascadeQuantity": false,
        "DefaultQuantity": null,
        "AllowProration": false,
        "HasCriteria": false,
        "DefaultSellingTerm": null,
        "IsSellingTermReadOnly": false,
        "Type": null,
        "ExpirationDate": "2100-12-31T00:00:00Z",
        "ChargeType": "Standard Price",
        "AutoCascadeSellingTerm": false,
        "ContractPrice": null,
        "Frequency": null,
        "IsUsageTierModifiable": false,
        "EffectiveDate": "1900-01-01T00:00:00Z",
        "PriceList": {
          "Currency": "USD",
          "Id": "ACS_PL",
          "Name": "ACS_PL",
          "Account": null,
          "BasedOnAdjustmentAmount": null,
          "BasedOnAdjustmentType": null,
          "ContractNumber": null,
          "Description": "ACS_PL",
          "EffectiveDate": "1900-01-01T00:00:00Z",
          "ExpirationDate": "2100-12-31T00:00:00Z",
          "IsActive": true,
          "Type": "Standard"
        }
      }
    ]
  }
]